[
    {
        "protected": false,
        "name": "BOBCATSSS Official",
        "id": "1271514340559126528",
        "username": "bobcatsssoffice",
        "public_metrics": {
            "followers_count": 224,
            "following_count": 1112,
            "tweet_count": 135,
            "listed_count": 2
        }
    },
    {
        "protected": false,
        "name": "Mohammad Aliannejadi",
        "id": "341000847",
        "username": "maliannejadi",
        "public_metrics": {
            "followers_count": 1175,
            "following_count": 1532,
            "tweet_count": 2327,
            "listed_count": 22
        }
    },
    {
        "protected": false,
        "name": "Rodger Benham",
        "id": "1265795638551212032",
        "username": "rodger_benham",
        "public_metrics": {
            "followers_count": 133,
            "following_count": 272,
            "tweet_count": 82,
            "listed_count": 1
        }
    },
    {
        "protected": false,
        "name": "Nirmal Roy",
        "id": "75525450",
        "username": "_nirmalroy",
        "public_metrics": {
            "followers_count": 319,
            "following_count": 561,
            "tweet_count": 260,
            "listed_count": 3
        }
    },
    {
        "protected": false,
        "name": "Shawon Sarkar",
        "id": "129475208",
        "username": "koyel2010",
        "public_metrics": {
            "followers_count": 152,
            "following_count": 386,
            "tweet_count": 101,
            "listed_count": 0
        }
    },
    {
        "protected": false,
        "name": "Chris Cyr",
        "id": "1161648767747203072",
        "username": "ChrisCyr19",
        "public_metrics": {
            "followers_count": 366,
            "following_count": 696,
            "tweet_count": 761,
            "listed_count": 7
        }
    },
    {
        "protected": false,
        "name": "Charlie Clarke",
        "id": "229601276",
        "username": "claclarke",
        "public_metrics": {
            "followers_count": 421,
            "following_count": 606,
            "tweet_count": 88,
            "listed_count": 9
        }
    },
    {
        "protected": false,
        "name": "ECIR 2020",
        "id": "1070321898951753728",
        "username": "ecir2020",
        "public_metrics": {
            "followers_count": 560,
            "following_count": 238,
            "tweet_count": 89,
            "listed_count": 0
        }
    },
    {
        "protected": false,
        "name": "ICTIR 2021",
        "id": "920700510306529280",
        "username": "acm_ictir",
        "public_metrics": {
            "followers_count": 643,
            "following_count": 343,
            "tweet_count": 71,
            "listed_count": 16
        }
    },
    {
        "protected": false,
        "name": "Elizabeth Churchill",
        "id": "7466492",
        "username": "xeeliz",
        "public_metrics": {
            "followers_count": 6663,
            "following_count": 534,
            "tweet_count": 871,
            "listed_count": 245
        }
    },
    {
        "protected": false,
        "name": "Marie Radford, Ph.D.",
        "id": "577283256",
        "username": "MarieLRadford",
        "public_metrics": {
            "followers_count": 1164,
            "following_count": 1556,
            "tweet_count": 2878,
            "listed_count": 24
        }
    },
    {
        "protected": false,
        "name": "Ahold Delhaize News",
        "id": "3343680741",
        "username": "AholdDelhaize",
        "public_metrics": {
            "followers_count": 2784,
            "following_count": 155,
            "tweet_count": 24,
            "listed_count": 64
        }
    },
    {
        "protected": false,
        "name": "Anne Goulding 🏴󠁧󠁢󠁷󠁬󠁳󠁿 🇳🇿",
        "id": "199629730",
        "username": "AnneGoulding",
        "public_metrics": {
            "followers_count": 1324,
            "following_count": 4138,
            "tweet_count": 5788,
            "listed_count": 16
        }
    },
    {
        "protected": false,
        "name": "Aylin Imeri (Ilhan)",
        "id": "391300597",
        "username": "Aylinnchen",
        "public_metrics": {
            "followers_count": 417,
            "following_count": 402,
            "tweet_count": 1769,
            "listed_count": 6
        }
    },
    {
        "protected": false,
        "name": "Centre for Information Discovery & Data Analytics",
        "id": "1187585868493537280",
        "username": "rmit_cidda",
        "public_metrics": {
            "followers_count": 169,
            "following_count": 120,
            "tweet_count": 173,
            "listed_count": 4
        }
    },
    {
        "protected": false,
        "name": "David Brazier",
        "id": "4053818032",
        "username": "BrazierPhD",
        "public_metrics": {
            "followers_count": 231,
            "following_count": 561,
            "tweet_count": 778,
            "listed_count": 10
        }
    },
    {
        "protected": false,
        "name": "Denise Agosto",
        "id": "1194321986748637184",
        "username": "DeniseEAgosto",
        "public_metrics": {
            "followers_count": 222,
            "following_count": 231,
            "tweet_count": 122,
            "listed_count": 1
        }
    },
    {
        "protected": false,
        "name": "Next Search",
        "id": "1206594224537448449",
        "username": "nextwebsearch",
        "public_metrics": {
            "followers_count": 97,
            "following_count": 1518,
            "tweet_count": 59,
            "listed_count": 3
        }
    },
    {
        "protected": false,
        "name": "Claudia Hauff",
        "id": "305474242",
        "username": "CharlotteHase",
        "public_metrics": {
            "followers_count": 2663,
            "following_count": 1411,
            "tweet_count": 5137,
            "listed_count": 93
        }
    },
    {
        "protected": false,
        "name": "Hamed Zamani",
        "id": "65915718",
        "username": "HamedZamani",
        "public_metrics": {
            "followers_count": 2167,
            "following_count": 1020,
            "tweet_count": 4898,
            "listed_count": 58
        }
    },
    {
        "protected": false,
        "name": "European Chapter (EC) ASIS&T",
        "id": "1118554900693159936",
        "username": "asist_ec",
        "public_metrics": {
            "followers_count": 190,
            "following_count": 227,
            "tweet_count": 186,
            "listed_count": 3
        }
    },
    {
        "protected": false,
        "name": "Edwin Mouda Ye",
        "id": "1582645148",
        "username": "YeEdwinM",
        "public_metrics": {
            "followers_count": 61,
            "following_count": 365,
            "tweet_count": 30,
            "listed_count": 0
        }
    },
    {
        "protected": false,
        "name": "Jaime Teevan",
        "id": "44973000",
        "username": "jteevan",
        "public_metrics": {
            "followers_count": 5244,
            "following_count": 1721,
            "tweet_count": 4476,
            "listed_count": 172
        }
    },
    {
        "protected": false,
        "name": "TerrierTeam",
        "id": "76679840",
        "username": "TerrierTeam",
        "public_metrics": {
            "followers_count": 873,
            "following_count": 60,
            "tweet_count": 1253,
            "listed_count": 33
        }
    },
    {
        "protected": false,
        "name": "CLEF eHealth Lab",
        "id": "3130548765",
        "username": "clefehealth",
        "public_metrics": {
            "followers_count": 284,
            "following_count": 49,
            "tweet_count": 171,
            "listed_count": 7
        }
    },
    {
        "protected": false,
        "name": "Gianmaria Silvello",
        "id": "22597445",
        "username": "giansilv",
        "public_metrics": {
            "followers_count": 514,
            "following_count": 699,
            "tweet_count": 3688,
            "listed_count": 0
        }
    },
    {
        "protected": false,
        "name": "iSchool at Illinois",
        "id": "17883396",
        "username": "iSchoolUI",
        "public_metrics": {
            "followers_count": 4586,
            "following_count": 1167,
            "tweet_count": 8546,
            "listed_count": 238
        }
    },
    {
        "protected": false,
        "name": "Soo Young Rieh",
        "id": "1104609567181340682",
        "username": "riehsooyoung",
        "public_metrics": {
            "followers_count": 136,
            "following_count": 72,
            "tweet_count": 39,
            "listed_count": 1
        }
    },
    {
        "protected": false,
        "name": "DESIRES2021",
        "id": "862356144748204032",
        "username": "DESIRES_IR",
        "public_metrics": {
            "followers_count": 388,
            "following_count": 115,
            "tweet_count": 205,
            "listed_count": 7
        }
    },
    {
        "protected": false,
        "name": "Nielsen Norman Group",
        "id": "15022225",
        "username": "NNgroup",
        "public_metrics": {
            "followers_count": 99772,
            "following_count": 49,
            "tweet_count": 2090,
            "listed_count": 4286
        }
    },
    {
        "protected": false,
        "name": "Bobcatsss 2020",
        "id": "1068504020153761793",
        "username": "bobcatsss2020",
        "public_metrics": {
            "followers_count": 198,
            "following_count": 45,
            "tweet_count": 225,
            "listed_count": 4
        }
    },
    {
        "protected": false,
        "name": "Lynn S. Connaway",
        "id": "25037133",
        "username": "LynnConnaway",
        "public_metrics": {
            "followers_count": 820,
            "following_count": 346,
            "tweet_count": 926,
            "listed_count": 36
        }
    },
    {
        "protected": false,
        "name": "Steve Krug",
        "id": "18544024",
        "username": "skrug",
        "public_metrics": {
            "followers_count": 77905,
            "following_count": 38,
            "tweet_count": 3197,
            "listed_count": 3064
        }
    },
    {
        "protected": false,
        "name": "Louis Rosenfeld",
        "id": "1760431",
        "username": "louisrosenfeld",
        "public_metrics": {
            "followers_count": 25017,
            "following_count": 1816,
            "tweet_count": 17275,
            "listed_count": 0
        }
    },
    {
        "protected": false,
        "name": "Digital Story_Social Informatics_AG",
        "id": "1098668320289636353",
        "username": "AW_Gardner",
        "public_metrics": {
            "followers_count": 6,
            "following_count": 140,
            "tweet_count": 0,
            "listed_count": 0
        }
    },
    {
        "protected": false,
        "name": "Information and Learning Sciences",
        "id": "1089876109469077504",
        "username": "InfoLearnJournl",
        "public_metrics": {
            "followers_count": 510,
            "following_count": 195,
            "tweet_count": 186,
            "listed_count": 9
        }
    },
    {
        "protected": false,
        "name": "ahasanhabib",
        "id": "860501901309231104",
        "username": "ahasanh78999480",
        "public_metrics": {
            "followers_count": 5,
            "following_count": 39,
            "tweet_count": 83,
            "listed_count": 0
        }
    },
    {
        "protected": false,
        "name": "Peter Morville",
        "id": "1230801",
        "username": "morville",
        "public_metrics": {
            "followers_count": 23330,
            "following_count": 79,
            "tweet_count": 11662,
            "listed_count": 1729
        }
    },
    {
        "protected": false,
        "name": "IA Institute",
        "id": "16140339",
        "username": "iainstitute",
        "public_metrics": {
            "followers_count": 18647,
            "following_count": 360,
            "tweet_count": 3278,
            "listed_count": 1106
        }
    },
    {
        "protected": false,
        "name": "IAC - information architecture conference #IAC22",
        "id": "14429880",
        "username": "theiaconf",
        "public_metrics": {
            "followers_count": 11194,
            "following_count": 2020,
            "tweet_count": 9781,
            "listed_count": 661
        }
    },
    {
        "protected": false,
        "name": "ECIR2019",
        "id": "966411199649808386",
        "username": "ecir2019",
        "public_metrics": {
            "followers_count": 367,
            "following_count": 53,
            "tweet_count": 195,
            "listed_count": 13
        }
    },
    {
        "protected": false,
        "name": "Mongolia",
        "id": "2294599093",
        "username": "mongolia_1206",
        "public_metrics": {
            "followers_count": 24495,
            "following_count": 1647,
            "tweet_count": 5816,
            "listed_count": 31
        }
    },
    {
        "protected": false,
        "name": "FIRE",
        "id": "296312612",
        "username": "fire_forum",
        "public_metrics": {
            "followers_count": 197,
            "following_count": 232,
            "tweet_count": 149,
            "listed_count": 8
        }
    },
    {
        "protected": false,
        "name": "planetoid",
        "id": "368463",
        "username": "planetoid",
        "public_metrics": {
            "followers_count": 389,
            "following_count": 903,
            "tweet_count": 2928,
            "listed_count": 10
        }
    },
    {
        "protected": false,
        "name": "Simone Laurent",
        "id": "4060762100",
        "username": "Canton_CiCi",
        "public_metrics": {
            "followers_count": 188,
            "following_count": 4219,
            "tweet_count": 1549,
            "listed_count": 1
        }
    },
    {
        "protected": false,
        "name": "Espacio Robot",
        "id": "854358733027237889",
        "username": "EspacioRobot",
        "public_metrics": {
            "followers_count": 103076,
            "following_count": 118356,
            "tweet_count": 2538,
            "listed_count": 328
        }
    },
    {
        "protected": false,
        "name": "@arjen@idf.social",
        "id": "16868154",
        "username": "arjenpdevries",
        "public_metrics": {
            "followers_count": 2316,
            "following_count": 1809,
            "tweet_count": 11666,
            "listed_count": 115
        }
    },
    {
        "protected": false,
        "name": "Krisztian Balog",
        "id": "91168371",
        "username": "krisztianbalog",
        "public_metrics": {
            "followers_count": 2096,
            "following_count": 280,
            "tweet_count": 1001,
            "listed_count": 74
        }
    },
    {
        "protected": false,
        "name": "@djoerd@idf.social",
        "id": "21133730",
        "username": "djoerd",
        "public_metrics": {
            "followers_count": 1176,
            "following_count": 817,
            "tweet_count": 5103,
            "listed_count": 33
        }
    },
    {
        "protected": false,
        "name": "Leif Azzopardi",
        "id": "25134469",
        "username": "leifos",
        "public_metrics": {
            "followers_count": 2001,
            "following_count": 974,
            "tweet_count": 4335,
            "listed_count": 74
        }
    },
    {
        "protected": false,
        "name": "Christine Borgman",
        "id": "27301650",
        "username": "SciTechProf",
        "public_metrics": {
            "followers_count": 1861,
            "following_count": 671,
            "tweet_count": 519,
            "listed_count": 104
        }
    },
    {
        "protected": false,
        "name": "Jeremy Pickens",
        "id": "22960511",
        "username": "jerepick",
        "public_metrics": {
            "followers_count": 680,
            "following_count": 342,
            "tweet_count": 1397,
            "listed_count": 58
        }
    },
    {
        "protected": false,
        "name": "Robert Capra",
        "id": "112202046",
        "username": "rcapra3",
        "public_metrics": {
            "followers_count": 258,
            "following_count": 60,
            "tweet_count": 370,
            "listed_count": 21
        }
    },
    {
        "protected": false,
        "name": "Journal of Library and Information Studies",
        "id": "1052731627233665024",
        "username": "JLIS_Taiwan",
        "public_metrics": {
            "followers_count": 36,
            "following_count": 36,
            "tweet_count": 216,
            "listed_count": 1
        }
    },
    {
        "protected": false,
        "name": "耕深",
        "id": "224209816",
        "username": "twitoogle",
        "public_metrics": {
            "followers_count": 174,
            "following_count": 401,
            "tweet_count": 536,
            "listed_count": 11
        }
    },
    {
        "protected": false,
        "name": "Lydia Middleton",
        "id": "181687556",
        "username": "Lydmid",
        "public_metrics": {
            "followers_count": 155,
            "following_count": 220,
            "tweet_count": 145,
            "listed_count": 3
        }
    },
    {
        "protected": false,
        "name": "ASIST SIG USE",
        "id": "955910820642344960",
        "username": "ASIST_SIGUSE",
        "public_metrics": {
            "followers_count": 44,
            "following_count": 89,
            "tweet_count": 9,
            "listed_count": 0
        }
    },
    {
        "protected": false,
        "name": "Chirag Shah",
        "id": "16632955",
        "username": "chirag_shah",
        "public_metrics": {
            "followers_count": 1090,
            "following_count": 68,
            "tweet_count": 1829,
            "listed_count": 70
        }
    },
    {
        "protected": false,
        "name": "Frank T. Hopfgartner",
        "id": "91697719",
        "username": "FTHopf",
        "public_metrics": {
            "followers_count": 891,
            "following_count": 622,
            "tweet_count": 1377,
            "listed_count": 43
        }
    },
    {
        "protected": false,
        "name": "Rebecca Reynolds",
        "id": "7300642",
        "username": "rbrbrbr",
        "public_metrics": {
            "followers_count": 574,
            "following_count": 2264,
            "tweet_count": 1165,
            "listed_count": 13
        }
    },
    {
        "protected": false,
        "name": "ACM CHIIR 2022",
        "id": "3041372326",
        "username": "ACM_CHIIR",
        "public_metrics": {
            "followers_count": 1408,
            "following_count": 452,
            "tweet_count": 1251,
            "listed_count": 40
        }
    },
    {
        "protected": false,
        "name": "Information Retrieval Journal",
        "id": "947311503216066560",
        "username": "SpringerIRJ",
        "public_metrics": {
            "followers_count": 613,
            "following_count": 218,
            "tweet_count": 20,
            "listed_count": 11
        }
    },
    {
        "protected": false,
        "name": "WSDM 2022 Conference",
        "id": "3107101390",
        "username": "WSDMSocial",
        "public_metrics": {
            "followers_count": 2352,
            "following_count": 115,
            "tweet_count": 709,
            "listed_count": 76
        }
    },
    {
        "protected": false,
        "name": "CIKM 2018",
        "id": "984135577208373249",
        "username": "cikm2018",
        "public_metrics": {
            "followers_count": 155,
            "following_count": 6,
            "tweet_count": 36,
            "listed_count": 9
        }
    },
    {
        "protected": false,
        "name": "BOBCATSSS 2019",
        "id": "942459317449580553",
        "username": "bobcatsss2019",
        "public_metrics": {
            "followers_count": 484,
            "following_count": 4687,
            "tweet_count": 96,
            "listed_count": 9
        }
    },
    {
        "protected": false,
        "name": "OIR journal",
        "id": "762580626339926016",
        "username": "OIRjournal",
        "public_metrics": {
            "followers_count": 150,
            "following_count": 301,
            "tweet_count": 443,
            "listed_count": 3
        }
    },
    {
        "protected": false,
        "name": "TheCanberra5",
        "id": "977053873977241601",
        "username": "TheCanberra5",
        "public_metrics": {
            "followers_count": 115,
            "following_count": 804,
            "tweet_count": 112,
            "listed_count": 0
        }
    },
    {
        "protected": false,
        "name": "AIRS 2018 Taipei",
        "id": "978159761421082625",
        "username": "airs2018",
        "public_metrics": {
            "followers_count": 25,
            "following_count": 12,
            "tweet_count": 6,
            "listed_count": 5
        }
    },
    {
        "protected": false,
        "name": "Md Shajalal",
        "id": "1721425735",
        "username": "shajalalhossain",
        "public_metrics": {
            "followers_count": 118,
            "following_count": 645,
            "tweet_count": 161,
            "listed_count": 3
        }
    },
    {
        "protected": false,
        "name": "ACM FAccT (formerly ACM FAT*)",
        "id": "897060827316072448",
        "username": "FAccTConference",
        "public_metrics": {
            "followers_count": 7586,
            "following_count": 61,
            "tweet_count": 1039,
            "listed_count": 150
        }
    },
    {
        "protected": false,
        "name": "Syracuse University iSchool",
        "id": "19035253",
        "username": "iSchoolSU",
        "public_metrics": {
            "followers_count": 10065,
            "following_count": 1476,
            "tweet_count": 22641,
            "listed_count": 584
        }
    },
    {
        "protected": false,
        "name": "Rutgers School of Communication and Information",
        "id": "52517689",
        "username": "RutgersCommInfo",
        "public_metrics": {
            "followers_count": 5351,
            "following_count": 959,
            "tweet_count": 50080,
            "listed_count": 0
        }
    },
    {
        "protected": false,
        "name": "Learning SPARQL",
        "id": "292580628",
        "username": "LearningSPARQL",
        "public_metrics": {
            "followers_count": 1953,
            "following_count": 195,
            "tweet_count": 3673,
            "listed_count": 125
        }
    },
    {
        "protected": false,
        "name": "Semantic Web Journal",
        "id": "145812829",
        "username": "SW_Journal",
        "public_metrics": {
            "followers_count": 3341,
            "following_count": 37,
            "tweet_count": 1319,
            "listed_count": 0
        }
    },
    {
        "protected": false,
        "name": "Aravind",
        "id": "29897913",
        "username": "aravindsr",
        "public_metrics": {
            "followers_count": 635,
            "following_count": 1619,
            "tweet_count": 4575,
            "listed_count": 21
        }
    },
    {
        "protected": false,
        "name": "Rob Sanderson",
        "id": "20148603",
        "username": "azaroth42",
        "public_metrics": {
            "followers_count": 2237,
            "following_count": 375,
            "tweet_count": 16294,
            "listed_count": 139
        }
    },
    {
        "protected": false,
        "name": "mwu",
        "id": "929251022",
        "username": "mwu2005",
        "public_metrics": {
            "followers_count": 3,
            "following_count": 63,
            "tweet_count": 7,
            "listed_count": 0
        }
    },
    {
        "protected": false,
        "name": "Milad Shokouhi",
        "id": "36417099",
        "username": "invertedindex",
        "public_metrics": {
            "followers_count": 628,
            "following_count": 161,
            "tweet_count": 129,
            "listed_count": 13
        }
    },
    {
        "protected": false,
        "name": "Ben Carterette",
        "id": "130671142",
        "username": "BenCarterette",
        "public_metrics": {
            "followers_count": 1835,
            "following_count": 634,
            "tweet_count": 561,
            "listed_count": 49
        }
    },
    {
        "protected": false,
        "name": "Andrew Trotman",
        "id": "305431714",
        "username": "andrew_trotman",
        "public_metrics": {
            "followers_count": 207,
            "following_count": 109,
            "tweet_count": 132,
            "listed_count": 4
        }
    },
    {
        "protected": false,
        "name": "Kevyn Collins-Thompson",
        "id": "33970089",
        "username": "kevynct",
        "public_metrics": {
            "followers_count": 520,
            "following_count": 998,
            "tweet_count": 371,
            "listed_count": 6
        }
    },
    {
        "protected": false,
        "name": "IMLS",
        "id": "36240331",
        "username": "US_IMLS",
        "public_metrics": {
            "followers_count": 26534,
            "following_count": 385,
            "tweet_count": 9869,
            "listed_count": 1056
        }
    },
    {
        "protected": false,
        "name": "HathiTrust",
        "id": "29622975",
        "username": "hathitrust",
        "public_metrics": {
            "followers_count": 13866,
            "following_count": 2830,
            "tweet_count": 1512,
            "listed_count": 508
        }
    },
    {
        "protected": false,
        "name": "ACRL",
        "id": "15723551",
        "username": "ALA_ACRL",
        "public_metrics": {
            "followers_count": 22059,
            "following_count": 681,
            "tweet_count": 5847,
            "listed_count": 985
        }
    },
    {
        "protected": false,
        "name": "ALISE HQ",
        "id": "991203720",
        "username": "alisehq",
        "public_metrics": {
            "followers_count": 1272,
            "following_count": 651,
            "tweet_count": 2822,
            "listed_count": 53
        }
    },
    {
        "protected": false,
        "name": "Strathclyde iSchool",
        "id": "906153421748793345",
        "username": "Strath_iSchool",
        "public_metrics": {
            "followers_count": 466,
            "following_count": 421,
            "tweet_count": 498,
            "listed_count": 7
        }
    },
    {
        "protected": false,
        "name": "ALPESHKUMAR J PARMAR",
        "id": "328877440",
        "username": "2333Parmar",
        "public_metrics": {
            "followers_count": 20,
            "following_count": 510,
            "tweet_count": 11,
            "listed_count": 0
        }
    },
    {
        "protected": false,
        "name": "Iadh Ounis",
        "id": "17078917",
        "username": "iadh",
        "public_metrics": {
            "followers_count": 2418,
            "following_count": 285,
            "tweet_count": 3937,
            "listed_count": 0
        }
    },
    {
        "protected": false,
        "name": "Nicola Ferro",
        "id": "3128829965",
        "username": "frrncl",
        "public_metrics": {
            "followers_count": 867,
            "following_count": 188,
            "tweet_count": 2652,
            "listed_count": 29
        }
    },
    {
        "protected": false,
        "name": "CLEF",
        "id": "3395161438",
        "username": "clef_initiative",
        "public_metrics": {
            "followers_count": 755,
            "following_count": 29,
            "tweet_count": 457,
            "listed_count": 0
        }
    },
    {
        "protected": false,
        "name": "ECIR 2018",
        "id": "804701761017671680",
        "username": "ecir2018",
        "public_metrics": {
            "followers_count": 428,
            "following_count": 28,
            "tweet_count": 141,
            "listed_count": 13
        }
    },
    {
        "protected": false,
        "name": "Hosein Azarbonyad",
        "id": "755648928",
        "username": "HAzarbonyad",
        "public_metrics": {
            "followers_count": 648,
            "following_count": 375,
            "tweet_count": 894,
            "listed_count": 19
        }
    },
    {
        "protected": false,
        "name": "Mostafa Dehghani",
        "id": "2550133394",
        "username": "m__dehghani",
        "public_metrics": {
            "followers_count": 2567,
            "following_count": 1084,
            "tweet_count": 1117,
            "listed_count": 50
        }
    },
    {
        "protected": false,
        "name": "Jaap Kamps",
        "id": "19677430",
        "username": "jkamps",
        "public_metrics": {
            "followers_count": 975,
            "following_count": 699,
            "tweet_count": 339,
            "listed_count": 19
        }
    },
    {
        "protected": false,
        "name": "Bruce Croft",
        "id": "59263220",
        "username": "wbc11",
        "public_metrics": {
            "followers_count": 1105,
            "following_count": 6,
            "tweet_count": 48,
            "listed_count": 22
        }
    },
    {
        "protected": false,
        "name": "ACM SIGIR 2018",
        "id": "3415864408",
        "username": "sigir2018",
        "public_metrics": {
            "followers_count": 535,
            "following_count": 11,
            "tweet_count": 117,
            "listed_count": 17
        }
    },
    {
        "protected": false,
        "name": "ACM SIGIR",
        "id": "2190533245",
        "username": "ACMSIGIR",
        "public_metrics": {
            "followers_count": 1580,
            "following_count": 825,
            "tweet_count": 93,
            "listed_count": 42
        }
    },
    {
        "protected": false,
        "name": "SIGIR Forum",
        "id": "2273201773",
        "username": "SIGIRForum",
        "public_metrics": {
            "followers_count": 990,
            "following_count": 125,
            "tweet_count": 146,
            "listed_count": 26
        }
    },
    {
        "protected": false,
        "name": "JASIST",
        "id": "589300441",
        "username": "JASIST",
        "public_metrics": {
            "followers_count": 4474,
            "following_count": 638,
            "tweet_count": 1793,
            "listed_count": 122
        }
    },
    {
        "protected": false,
        "name": "Library Journal",
        "id": "15169290",
        "username": "LibraryJournal",
        "public_metrics": {
            "followers_count": 243180,
            "following_count": 410,
            "tweet_count": 50795,
            "listed_count": 5854
        }
    },
    {
        "protected": false,
        "name": "American Libraries",
        "id": "18955776",
        "username": "amlibraries",
        "public_metrics": {
            "followers_count": 96730,
            "following_count": 1140,
            "tweet_count": 31672,
            "listed_count": 2310
        }
    },
    {
        "protected": false,
        "name": "CILIP InfoLit Group",
        "id": "223880738",
        "username": "infolitgroup",
        "public_metrics": {
            "followers_count": 7202,
            "following_count": 1543,
            "tweet_count": 4522,
            "listed_count": 245
        }
    },
    {
        "protected": false,
        "name": "American Library Association",
        "id": "21799699",
        "username": "ALALibrary",
        "public_metrics": {
            "followers_count": 224764,
            "following_count": 4317,
            "tweet_count": 27544,
            "listed_count": 4079
        }
    },
    {
        "protected": false,
        "name": "ASIS&T EuropStudChap",
        "id": "4413508635",
        "username": "asist_esc",
        "public_metrics": {
            "followers_count": 90,
            "following_count": 24,
            "tweet_count": 59,
            "listed_count": 2
        }
    },
    {
        "protected": false,
        "name": "CILIP",
        "id": "61518146",
        "username": "CILIPinfo",
        "public_metrics": {
            "followers_count": 27869,
            "following_count": 3513,
            "tweet_count": 50712,
            "listed_count": 1085
        }
    },
    {
        "protected": false,
        "name": "ASIS&T SIG AH",
        "id": "2951809727",
        "username": "asist_ah",
        "public_metrics": {
            "followers_count": 201,
            "following_count": 153,
            "tweet_count": 688,
            "listed_count": 7
        }
    },
    {
        "protected": false,
        "name": "ASIS&T SIG HLTH",
        "id": "448365862",
        "username": "sighlth",
        "public_metrics": {
            "followers_count": 126,
            "following_count": 13,
            "tweet_count": 55,
            "listed_count": 6
        }
    },
    {
        "protected": false,
        "name": "ASIS&T SIG SI",
        "id": "208195843",
        "username": "ASISTsigSI",
        "public_metrics": {
            "followers_count": 697,
            "following_count": 300,
            "tweet_count": 748,
            "listed_count": 36
        }
    },
    {
        "protected": false,
        "name": "IFLA",
        "id": "53361561",
        "username": "IFLA",
        "public_metrics": {
            "followers_count": 31718,
            "following_count": 452,
            "tweet_count": 4402,
            "listed_count": 1090
        }
    },
    {
        "protected": false,
        "name": "OCLC",
        "id": "29516133",
        "username": "OCLC",
        "public_metrics": {
            "followers_count": 30801,
            "following_count": 1185,
            "tweet_count": 16971,
            "listed_count": 1397
        }
    },
    {
        "protected": false,
        "name": "LIS Research",
        "id": "64693923",
        "username": "LISResearch",
        "public_metrics": {
            "followers_count": 8670,
            "following_count": 78,
            "tweet_count": 14698,
            "listed_count": 483
        }
    },
    {
        "protected": false,
        "name": "iSchools iConference",
        "id": "614716389",
        "username": "iconf",
        "public_metrics": {
            "followers_count": 1836,
            "following_count": 534,
            "tweet_count": 1341,
            "listed_count": 0
        }
    },
    {
        "protected": false,
        "name": "Dublin Core",
        "id": "60715051",
        "username": "DublinCore",
        "public_metrics": {
            "followers_count": 6837,
            "following_count": 426,
            "tweet_count": 4070,
            "listed_count": 584
        }
    },
    {
        "protected": false,
        "name": "iSchools",
        "id": "19073790",
        "username": "iSchools",
        "public_metrics": {
            "followers_count": 4079,
            "following_count": 694,
            "tweet_count": 4604,
            "listed_count": 210
        }
    },
    {
        "protected": false,
        "name": "ASIS&T",
        "id": "63801028",
        "username": "asist_org",
        "public_metrics": {
            "followers_count": 7238,
            "following_count": 1795,
            "tweet_count": 10752,
            "listed_count": 458
        }
    },
    {
        "protected": true,
        "name": "YooJin Ha",
        "id": "367593663",
        "username": "arias0330",
        "public_metrics": {
            "followers_count": 68,
            "following_count": 132,
            "tweet_count": 73,
            "listed_count": 0
        }
    },
    {
        "protected": false,
        "name": "Ralf Bierig",
        "id": "2558691000",
        "username": "ralf_bierig",
        "public_metrics": {
            "followers_count": 33,
            "following_count": 46,
            "tweet_count": 31,
            "listed_count": 1
        }
    },
    {
        "protected": false,
        "name": "Nora Bird",
        "id": "287695297",
        "username": "NorajBird",
        "public_metrics": {
            "followers_count": 210,
            "following_count": 104,
            "tweet_count": 85,
            "listed_count": 9
        }
    },
    {
        "protected": false,
        "name": "Mark Sanderson",
        "id": "127894322",
        "username": "IR_oldie",
        "public_metrics": {
            "followers_count": 2984,
            "following_count": 208,
            "tweet_count": 2165,
            "listed_count": 76
        }
    },
    {
        "protected": false,
        "name": "Marianne Lykke",
        "id": "224591498",
        "username": "mlykk",
        "public_metrics": {
            "followers_count": 32,
            "following_count": 4,
            "tweet_count": 1,
            "listed_count": 0
        }
    },
    {
        "protected": false,
        "name": "Maarten de Rijke",
        "id": "3304471",
        "username": "mdr",
        "public_metrics": {
            "followers_count": 3253,
            "following_count": 97,
            "tweet_count": 2451,
            "listed_count": 90
        }
    },
    {
        "protected": false,
        "name": "Kyong Eun Oh",
        "id": "2324416140",
        "username": "keoh0804",
        "public_metrics": {
            "followers_count": 187,
            "following_count": 85,
            "tweet_count": 219,
            "listed_count": 4
        }
    },
    {
        "protected": false,
        "name": "Koraljka Golub",
        "id": "2334825301",
        "username": "koraljkagolub",
        "public_metrics": {
            "followers_count": 59,
            "following_count": 21,
            "tweet_count": 3,
            "listed_count": 0
        }
    },
    {
        "protected": false,
        "name": "Jonas Fransson",
        "id": "24528242",
        "username": "jotifr",
        "public_metrics": {
            "followers_count": 153,
            "following_count": 383,
            "tweet_count": 419,
            "listed_count": 9
        }
    },
    {
        "protected": false,
        "name": "Researcher",
        "id": "3024542187",
        "username": "jimjansen1960",
        "public_metrics": {
            "followers_count": 8,
            "following_count": 201,
            "tweet_count": 7,
            "listed_count": 0
        }
    },
    {
        "protected": false,
        "name": "irene lopatovska",
        "id": "1503054096",
        "username": "irenelopapratt",
        "public_metrics": {
            "followers_count": 45,
            "following_count": 7,
            "tweet_count": 5,
            "listed_count": 2
        }
    },
    {
        "protected": false,
        "name": "/home/ggdupont",
        "id": "181208991",
        "username": "ggdupont",
        "public_metrics": {
            "followers_count": 254,
            "following_count": 653,
            "tweet_count": 5747,
            "listed_count": 31
        }
    },
    {
        "protected": false,
        "name": "Gunilla Widén",
        "id": "283662574",
        "username": "gunillawiden",
        "public_metrics": {
            "followers_count": 245,
            "following_count": 142,
            "tweet_count": 217,
            "listed_count": 0
        }
    },
    {
        "protected": false,
        "name": "Dirk Lewandowski",
        "id": "94581878",
        "username": "Dirk_Lew",
        "public_metrics": {
            "followers_count": 958,
            "following_count": 83,
            "tweet_count": 484,
            "listed_count": 40
        }
    },
    {
        "protected": false,
        "name": "Marianne Martens",
        "id": "26662308",
        "username": "MariLib",
        "public_metrics": {
            "followers_count": 468,
            "following_count": 1498,
            "tweet_count": 970,
            "listed_count": 11
        }
    },
    {
        "protected": false,
        "name": "Marcia Zeng",
        "id": "173588758",
        "username": "marciazeng",
        "public_metrics": {
            "followers_count": 566,
            "following_count": 61,
            "tweet_count": 765,
            "listed_count": 0
        }
    },
    {
        "protected": false,
        "name": "Gerry Grenier",
        "id": "25312220",
        "username": "gpgrenier",
        "public_metrics": {
            "followers_count": 434,
            "following_count": 142,
            "tweet_count": 516,
            "listed_count": 10
        }
    },
    {
        "protected": false,
        "name": "Nicholas Belkin",
        "id": "1499539130",
        "username": "njbelkin",
        "public_metrics": {
            "followers_count": 35,
            "following_count": 3,
            "tweet_count": 7,
            "listed_count": 0
        }
    },
    {
        "protected": false,
        "name": "Arizona iSchool",
        "id": "4205958313",
        "username": "uaischool",
        "public_metrics": {
            "followers_count": 5,
            "following_count": 0,
            "tweet_count": 2,
            "listed_count": 0
        }
    },
    {
        "protected": false,
        "name": "Seth van Hooland",
        "id": "64245814",
        "username": "sethvanhooland",
        "public_metrics": {
            "followers_count": 1506,
            "following_count": 999,
            "tweet_count": 1780,
            "listed_count": 74
        }
    },
    {
        "protected": false,
        "name": "Patricia K.",
        "id": "499420054",
        "username": "KuoPatricia",
        "public_metrics": {
            "followers_count": 7,
            "following_count": 1,
            "tweet_count": 0,
            "listed_count": 1
        }
    },
    {
        "protected": false,
        "name": "Dr Ross J Todd",
        "id": "38631450",
        "username": "RossJTodd",
        "public_metrics": {
            "followers_count": 2517,
            "following_count": 208,
            "tweet_count": 967,
            "listed_count": 172
        }
    },
    {
        "protected": true,
        "name": "Ying Sun",
        "id": "1201360238",
        "username": "YSYingsun",
        "public_metrics": {
            "followers_count": 4,
            "following_count": 5,
            "tweet_count": 6,
            "listed_count": 0
        }
    },
    {
        "protected": false,
        "name": "Chu Kai Wah",
        "id": "308884736",
        "username": "samchu1963",
        "public_metrics": {
            "followers_count": 27,
            "following_count": 4,
            "tweet_count": 7,
            "listed_count": 0
        }
    },
    {
        "protected": false,
        "name": "Ingo Frommholz",
        "id": "78269677",
        "username": "iFromm",
        "public_metrics": {
            "followers_count": 1243,
            "following_count": 1201,
            "tweet_count": 6958,
            "listed_count": 73
        }
    },
    {
        "protected": false,
        "name": "Rui Huang",
        "id": "22102635",
        "username": "DecadentRay",
        "public_metrics": {
            "followers_count": 2,
            "following_count": 0,
            "tweet_count": 13,
            "listed_count": 0
        }
    },
    {
        "protected": false,
        "name": "Prof/Dr Lisa M Given 🇨🇦🇦🇺",
        "id": "97316192",
        "username": "lisagiven",
        "public_metrics": {
            "followers_count": 2161,
            "following_count": 2536,
            "tweet_count": 5355,
            "listed_count": 0
        }
    },
    {
        "protected": false,
        "name": "Linh Nguyen",
        "id": "35179031",
        "username": "nclinh",
        "public_metrics": {
            "followers_count": 15,
            "following_count": 45,
            "tweet_count": 17,
            "listed_count": 0
        }
    },
    {
        "protected": false,
        "name": "Debbie Rabina",
        "id": "101862587",
        "username": "Debbie_Rabina",
        "public_metrics": {
            "followers_count": 384,
            "following_count": 160,
            "tweet_count": 536,
            "listed_count": 15
        }
    },
    {
        "protected": false,
        "name": "Mega Subramaniam",
        "id": "221927096",
        "username": "mmsubram",
        "public_metrics": {
            "followers_count": 1311,
            "following_count": 989,
            "tweet_count": 3793,
            "listed_count": 84
        }
    },
    {
        "protected": false,
        "name": "Inst. for arkiv-, bibliotek- og informasjonsfag",
        "id": "2546182795",
        "username": "OsloMet_ABI",
        "public_metrics": {
            "followers_count": 575,
            "following_count": 109,
            "tweet_count": 1085,
            "listed_count": 13
        }
    },
    {
        "protected": false,
        "name": "Hong Cui",
        "id": "1546621195",
        "username": "hongcuiTucson",
        "public_metrics": {
            "followers_count": 6,
            "following_count": 5,
            "tweet_count": 3,
            "listed_count": 0
        }
    },
    {
        "protected": false,
        "name": "julia kiseleva",
        "id": "2354542969",
        "username": "julia_kiseleva",
        "public_metrics": {
            "followers_count": 1040,
            "following_count": 361,
            "tweet_count": 1643,
            "listed_count": 30
        }
    },
    {
        "protected": false,
        "name": "Jia Tina Du",
        "id": "2472210714",
        "username": "dujiarainy",
        "public_metrics": {
            "followers_count": 451,
            "following_count": 666,
            "tweet_count": 955,
            "listed_count": 9
        }
    },
    {
        "protected": false,
        "name": "Ying-Hsang Liu",
        "id": "23761309",
        "username": "ruyhliu",
        "public_metrics": {
            "followers_count": 668,
            "following_count": 1343,
            "tweet_count": 1408,
            "listed_count": 42
        }
    }
]